{
  "bicolor": [
    "Autumn",
    "Binary",
    "Blues",
    "Bone",
    "BuGn",
    "Buda",
    "Cool",
    "Copper",
    "Devon",
    "GistHeat",
    "GrayC",
    "Grays",
    "Greens",
    "Lemon",
    "OrRd",
    "Oranges",
    "Oslo",
    "PuBu",
    "PuRd",
    "Purple",
    "Purples",
    "RdPu",
    "Reds",
    "Spring",
    "Summer",
    "Winter",
    "Wistia",
    "YlGn",
    "YlOrBr",
    "YlOrRd"
  ],
  "big-var": [
    "Accent",
    "ColorBlind",
    "Dark2",
    "Fes",
    "Flag",
    "GistStern",
    "GreenOrange",
    "Paired",
    "Pastel1",
    "Pastel2",
    "Prism",
    "Set1",
    "Set2",
    "Set3",
    "Tab10",
    "Tab20",
    "Tab20b",
    "Tab20c",
    "Tableau",
    "TableauLight",
    "TableauMedium",
    "TrafficLight"
  ],
  "deficient-blind": [
    "Acton",
    "Bam",
    "Bamako",
    "BamO",
    "Batlow",
    "BatlowK",
    "BatlowW",
    "Berlin",
    "Bilbao",
    "Broc",
    "BrocO",
    "Buda",
    "Bukavu",
    "Cork",
    "CorkO",
    "Davos",
    "Devon",
    "Fes",
    "Glasgow",
    "GrayC",
    "Hawaii",
    "Imola",
    "Lajolla",
    "Lapaz",
    "Lipari",
    "Lisbon",
    "Managua",
    "Navia",
    "NaviaW",
    "Nuuk",
    "Oleron",
    "Oslo",
    "Roma",
    "RomaO",
    "Tofino",
    "Tokyo",
    "Turku",
    "Vanimo",
    "Vik",
    "VikO"
  ],
  "rainbow": [
    "Batlow",
    "BatlowK",
    "BatlowW",
    "BlindFish",
    "BlueRed",
    "Brg",
    "Bukavu",
    "CMRmap",
    "Cubehelix",
    "Cubehelix1",
    "Cubehelix2",
    "GasFlame",
    "GeoRainbow",
    "GistEarth",
    "GistNcar",
    "GistRainbow",
    "Gnuplot",
    "Gnuplot2",
    "Hawaii",
    "Hsv",
    "Inferno",
    "Jet",
    "Lipari",
    "Lisbon",
    "Magma",
    "Managua",
    "NipySpectral",
    "Ocean",
    "Oleron",
    "PastelRainbow",
    "PerceptualRainbow",
    "Plasma",
    "PurpleGray",
    "Rainbow",
    "Roma",
    "RomaO",
    "ShiftRainbow",
    "Spectral",
    "Terrain",
    "Tofino",
    "Turbo",
    "Twilight",
    "TwilightShifted",
    "Vik",
    "VikO",
    "Viridis"
  ],
  "tricolor": [
    "Acton",
    "Afmhot",
    "Bam",
    "BamO",
    "Bamako",
    "Berlin",
    "Bilbao",
    "BrBG",
    "Broc",
    "BrocO",
    "BuPu",
    "BurningGrass",
    "Bwr",
    "Cividis",
    "Coolwarm",
    "Cork",
    "CorkO",
    "Cubehelix3",
    "Davos",
    "Glasgow",
    "GnBu",
    "Hot",
    "Imola",
    "JimSpecial",
    "Lajolla",
    "Lapaz",
    "Navia",
    "NaviaW",
    "Nuuk",
    "PRGn",
    "PiYG",
    "Pink",
    "PuBuGn",
    "PuOr",
    "RdBu",
    "RdGy",
    "RdYlBu",
    "RdYlGn",
    "Red",
    "Seismic",
    "Tokyo",
    "Turku",
    "Vanimo",
    "YlGnBu"
  ]
}